tests/__init__.py
tests/test_6.py
DataVEDA-0.0.2.dist-info/LICENSE
DataVEDA-0.0.2.dist-info/METADATA
DataVEDA-0.0.2.dist-info/WHEEL
DataVEDA-0.0.2.dist-info/top_level.txt
DataVEDA-0.0.2.dist-info/RECORD
