Metadata-Version: 2.1
Name: DataVEDA
Version: 0.0.2
Summary: DataVEDA is a Python library designed to streamline the data preprocessing and cleaning workflow for machine learning projects. It offers a comprehensive set of tools to handle common data preparation tasks
Home-page: https://github.com/vishallmaurya/VEDA
Author: Vishal Maurya
Author-email: vishallmaurya210@gmail.com
License: Apache License 2.0
Project-URL: Bug Tracker, https://github.com/vishallmaurya/VEDA/issues
Keywords: Automated Data Preprocessing,Data Cleaning,Data Balancing,Machine Learning,Data Transformation,Feature Engineering,Data Wrangling,Data Preparation
Classifier: Programming Language :: Python :: 3.9
Classifier: Programming Language :: Python :: 3.10
Classifier: Programming Language :: Python :: 3.11
Classifier: License :: OSI Approved :: Apache Software License
Classifier: Operating System :: OS Independent
Requires-Python: >=3.9
License-File: LICENSE
Requires-Dist: numpy >=1.21.0
Requires-Dist: pandas >=1.3.0
Requires-Dist: scikit-learn >=0.24.0
Requires-Dist: imbalanced-learn >=0.8.0
Requires-Dist: tensorflow >=2.4.0
Requires-Dist: umap-learn >=0.5.0
Requires-Dist: optuna >=2.7.0
Requires-Dist: statsmodels >=0.12.0
Requires-Dist: diptest >=0.1.0
Provides-Extra: dev
Requires-Dist: pytest >=6.0.0 ; extra == 'dev'
